eastmoneypy/__init__.py
eastmoneypy/api.py
eastmoneypy/config.json
eastmoneypy-0.2.0.dist-info/licenses/LICENSE
eastmoneypy-0.2.0.dist-info/METADATA
eastmoneypy-0.2.0.dist-info/WHEEL
eastmoneypy-0.2.0.dist-info/top_level.txt
eastmoneypy-0.2.0.dist-info/RECORD
