Metadata-Version: 2.4
Name: eastmoneypy
Version: 0.2.0
Summary: python lib for operating eastmoney
Home-page: https://github.com/zvtvz/eastmoneypy
Author: foolcage
Author-email: 5533061@qq.com
Project-URL: Bug Reports, https://github.com/zvtvz/eastmoneypy/issues
Project-URL: Funding, https://www.foolcage.com
Project-URL: Say Thanks!, https://saythanks.io/to/foolcage
Project-URL: Source, https://github.com/zvtvz/eastmoneypy
Keywords: eastmoney python
Classifier: Development Status :: 5 - Production/Stable
Classifier: Intended Audience :: Developers
Classifier: Intended Audience :: Customer Service
Classifier: Intended Audience :: Education
Classifier: Intended Audience :: Financial and Insurance Industry
Classifier: Topic :: Software Development :: Build Tools
Classifier: Topic :: Office/Business :: Financial :: Investment
Classifier: License :: OSI Approved :: MIT License
Classifier: Programming Language :: Python :: 3.9
Classifier: Programming Language :: Python :: 3.10
Classifier: Programming Language :: Python :: 3.11
Classifier: Programming Language :: Python :: 3.12
License-File: LICENSE
Requires-Dist: requests>=2.32.0
Requires-Dist: demjson3>=3.0.6
Dynamic: author
Dynamic: author-email
Dynamic: classifier
Dynamic: description
Dynamic: description-content-type
Dynamic: home-page
Dynamic: keywords
Dynamic: license-file
Dynamic: project-url
Dynamic: requires-dist
Dynamic: summary
